LICENSE
MANIFEST.in
README.md
setup.py
django_wfs.egg-info/PKG-INFO
django_wfs.egg-info/SOURCES.txt
django_wfs.egg-info/dependency_links.txt
django_wfs.egg-info/top_level.txt
wfs/__init__.py
wfs/admin.py
wfs/apps.py
wfs/models.py
wfs/tests.py
wfs/urls.py
wfs/views.py
wfs/templates/describeFeatureType.xml
wfs/templates/exception.xml
wfs/templates/getCapabilities.xml
wfs/templates/getFeature.xml