Metadata-Version: 1.1
Name: django-wfs
Version: 0.0.5
Summary: A WFS (web feature service) implementation as a Django application.
Home-page: https://github.com/vascop/django-wfs
Author: Vasco Pinho
Author-email: vascogpinho@gmail.com
License: Apache 2.0
Download-URL: https://github.com/vascop/django-wfs/tarball/master
Keywords: wfs,geo,django
Platform: UNKNOWN
Classifier: Environment :: Web Environment
Classifier: Framework :: Django
Classifier: Intended Audience :: Developers
